poetry_grpc_plugin/__init__.py
poetry_grpc_plugin/plugins.py
poetry_grpc_plugin-0.1.9.dist-info/LICENSE
poetry_grpc_plugin-0.1.9.dist-info/METADATA
poetry_grpc_plugin-0.1.9.dist-info/WHEEL
poetry_grpc_plugin-0.1.9.dist-info/entry_points.txt
poetry_grpc_plugin-0.1.9.dist-info/RECORD
