Metadata-Version: 2.1
Name: poetry-grpc-plugin
Version: 0.1.9
Summary: gRPC Poetry plugin
Home-page: https://github.com/fedej/poetry-grpc-plugin
License: MIT
Author: Federico Jaite
Author-email: fede_654_87@hotmail.com
Requires-Python: >=3.7,<4.0
Classifier: Development Status :: 3 - Alpha
Classifier: Intended Audience :: Developers
Classifier: License :: OSI Approved :: MIT License
Classifier: Operating System :: OS Independent
Classifier: Programming Language :: Python :: 3
Classifier: Programming Language :: Python :: 3.7
Classifier: Programming Language :: Python :: 3.8
Classifier: Programming Language :: Python :: 3.9
Classifier: Programming Language :: Python :: 3.10
Classifier: Programming Language :: Python :: 3.11
Classifier: Programming Language :: Python :: 3.12
Classifier: Programming Language :: Python :: 3 :: Only
Classifier: Topic :: Software Development :: Code Generators
Requires-Dist: grpcio-tools (>=1.39.0,<2.0.0)
Requires-Dist: mypy-protobuf (>=2.9,<4.0)
Requires-Dist: poetry (>=1.2.0,<2.0)
Project-URL: Repository, https://github.com/fedej/poetry-grpc-plugin
